odoo8_addon_shopinvader_product_link-8.0.1.0.0.99.dev5-py3.8-nspkg.pth
odoo_addons/shopinvader_product_link/README.rst
odoo_addons/shopinvader_product_link/__init__.py
odoo_addons/shopinvader_product_link/__openerp__.py
odoo_addons/shopinvader_product_link/data/ir_export.xml
odoo_addons/shopinvader_product_link/models/__init__.py
odoo_addons/shopinvader_product_link/models/product.py
odoo8_addon_shopinvader_product_link-8.0.1.0.0.99.dev5.dist-info/METADATA
odoo8_addon_shopinvader_product_link-8.0.1.0.0.99.dev5.dist-info/WHEEL
odoo8_addon_shopinvader_product_link-8.0.1.0.0.99.dev5.dist-info/namespace_packages.txt
odoo8_addon_shopinvader_product_link-8.0.1.0.0.99.dev5.dist-info/top_level.txt
odoo8_addon_shopinvader_product_link-8.0.1.0.0.99.dev5.dist-info/RECORD
